{"filesize_bytes":655967,"mimetype":"application/pdf","metadata":{"people":["['user']","user"],"date":["2013-07-24T10:33:29+12:00","2013-07-24T12:36:43+12:00"],"misc":{"dc_subject":["[]"],"dc_type":["[]"],"dc_publisher":["[]"],"cache":["{}"],"dc_date":["[]"],"dc_relation":["[]"],"dc_language":["[]"],"custom_properties":["{}"],"dc_contributor":["[]"],"dc_rights":["{}"],"dc_description":["{}"]},"software":["Acrobat Distiller 10.1.3 (Windows)","PScript5.dll Version 5.2.2"]},"filename":"FF-Farm-Confidence-Survey-July-2013.pdf","sha1":"c523a2e59142902735a380bbb90b48b98b005d96","children":[{"date":[]},{"date":[]},{"date":[]},{"date":[]},{"date":[]},{"date":[]},{"date":[]},{"date":[]},{"date":[]},{"date":[]},{"date":[]},{"date":[]},{"date":[]},{"date":[]},{"date":[]},{"date":[]},{"date":[]},{"date":[]},{"date":[]},{"date":[]},{"date":[]},{"date":[]},{"date":[]},{"date":[]},{"date":[]}],"url":"fedfarm.org.nz@@http://www.fedfarm.org.nz/Files/FF-Farm-Confidence-Survey-July-2013.pdf"}