{"mimetype":"application/pdf","filesize_bytes":204397,"sha1":"53cd9d247e9260a5465826f679aa53bbd3ac7595","metadata":{"xmp":{},"info":{"/CreationDate":"D:20130531154408+12'00'","/Creator":"Microsoft® Word 2010","/ModDate":"D:20130531154408+12'00'","/Author":"Richard Gardner","/Title":"Introduction","/Producer":"Microsoft® Word 2010"}},"filename":"Auckland-City-Council-DUP-policies-&-objectives.pdf","url":"fedfarm.org.nz@@http://www.fedfarm.org.nz/Files/Auckland-City-Council-DUP-policies-&-objectives.pdf"}