{"sha1":"0adf6c6b6fd3836bcdf707100dee66c4ed72aeac","filesize_bytes":59902,"filename":"mangatawhiri-river_buckingsham-bridge-lyons-road-2.jpg","metadata":{"exif:DateTime":"2014:01:22 10:45:04","icc:model":"IEC 61966-2.1 Default RGB colour space - sRGB","icc:description":"sRGB IEC61966-2.1","icc:manufacturer":"IEC http://www.iec.ch","exif:Software":"Adobe Photoshop CS6 (Windows)","icc:copyright":"Copyright (c) 1998 Hewlett-Packard Company"},"mimetype":"image/jpeg","url":"lawa.org.nz@@http://www.lawa.org.nz/media/17236/mangatawhiri-river_buckingsham-bridge-lyons-road-2.jpg"}