{"metadata":{"software":["DSC-W350"],"misc":{"exif:Saturation":["0"],"exif:DateTimeDigitized":["2013:01:24 09:50:34"],"exif:thumbnail:DateTime":["2013:01:24 09:50:34"],"exif:FileSource":["3"],"exif:Sharpness":["0"],"exif:SceneType":["1"],"exif:thumbnail:Orientation":["1"],"exif:Contrast":["0"],"exif:thumbnail:YResolution":["72/1"],"exif:DateTimeOriginal":["2013:01:24 09:50:34"],"exif:thumbnail:ResolutionUnit":["2"],"exif:thumbnail:InteroperabilityIndex":["R98"],"exif:MakerNote":["83, 79, 78, 89, 32, 68, 83, 67, 32, 0, 0, 0, 43, 0, 0, 32, 7, 0, 1, 0, 0, 0, 0, 0, 0, 0, 10, 32, 4, 0, 1, 0, 0, 0, 0, 0, 0, 0, 0, 48, 7, 0, 72, 1, 0, 0, 218, 4, 0, 0, 32, 176, 2, 0, 9, 0, 0, 0, 34, 6, 0, 0, 1, 144, 7, 0, 88, 2, 0, 0, 44, 6, 0, 0, 2, 144, 7, 0, 68, 1, 0, 0, 132, 8, 0, 0, 3, 144, 7, 0, 176, 1, 0, 0, 200, 9, 0, 0, 4, 144, 7, 0, 28, 2, 0, 0, 120, 11, 0, 0, 5, 144, 7, 0, 200, 2, 0, 0, 148, 13, 0, 0, 6, 144, 7, 0, 68, 4, 0, 0, 92, 16, 0, 0, 7, 144, 7, 0, 144, 1, 0, 0, 160, 20, 0, 0, 8, 144, 7, 0, 144, 1, 0, 0, 48, 22, 0, 0, 9, 144, 7, 0, 0, 1, 0, 0, 192, 23, 0, 0, 10, 144, 7, 0, 200, 0, 0, 0, 192, 24, 0, 0, 11, 144, 7, 0, 144, 1, 0, 0, 136, 25, 0, 0, 12, 144, 7, 0, 244, 1, 0, 0, 24, 27, 0, 0, 64, 176, 3, 0, 1, 0, 0, 0, 0, 0, 0, 0, 65, 176, 3, 0, 1, 0, 0, 0, 6, 0, 0, 0, 66, 176, 3, 0, 1, 0, 0, 0, 4, 0, 0, 0, 67, 176, 3, 0, 1, 0, 0, 0, 1, 0, 0, 0, 68, 176, 3, 0, 1, 0, 0, 0, 1, 0, 0, 0, 69, 176, 3, 0, 1, 0, 0, 0, 0, 0, 0, 0, 70, 176, 3, 0, 1, 0, 0, 0, 0, 0, 0, 0, 71, 176, 3, 0, 1, 0, 0, 0, 0, 0, 0, 0, 72, 176, 8, 0, 1, 0, 0, 0, 0, 0, 0, 0, 73, 176, 3, 0, 1, 0, 0, 0, 0, 0, 0, 0, 74, 176, 3, 0, 1, 0, 0, 0, 0, 0, 0, 0, 75, 176, 3, 0, 1, 0, 0, 0, 2, 0, 0, 0, 76, 176, 5, 0, 1, 0, 0, 0, 12, 29, 0, 0, 77, 176, 3, 0, 1, 0, 0, 0, 0, 0, 0, 0, 78, 176, 3, 0, 1, 0, 0, 0, 0, 0, 0, 0, 79, 176, 3, 0, 1, 0, 0, 0, 1, 0, 0, 0, 80, 176, 3, 0, 1, 0, 0, 0, 0, 0, 0, 0, 81, 176, 3, 0, 1, 0, 0, 0, 0, 0, 0, 0, 82, 176, 3, 0, 1, 0, 0, 0, 1, 0, 0, 0, 83, 176, 3, 0, 1, 0, 0, 0, 0, 0, 0, 0, 84, 176, 3, 0, 1, 0, 0, 0, 0, 0, 0, 0, 0, 160, 4, 0, 1, 0, 0, 0, 14, 0, 0, 128, 1, 160, 1, 0, 1, 0, 0, 0, 0, 0, 0, 0, 0, 161, 7, 0, 168, 0, 0, 0, 20, 29, 0, 0, 1, 161, 7, 0, 148, 1, 0, 0, 188, 29, 0, 0, 0, 162, 7, 0, 84, 10, 0, 0, 80, 31, 0, 0, 0, 167, 7, 0, 44, 0, 0, 0, 164, 41, 0, 0, 73, 73, 72, 0, 1, 1, 50, 48, 49, 51, 58, 48, 49, 58, 50, 52, 32, 48, 57, 58, 53, 48, 58, 51, 52, 0, 168, 12, 224, 16, 0, 0, 210, 3, 0, 0, 0, 0, 0, 0, 0, 0, 0, 0, 0, 0, 0, 0, 0, 0, 32, 0, 68, 67, 54, 51, 48, 51, 51, 50, 48, 50, 50, 50, 48, 48, 48, 0, 0, 0, 0, 0, 0, 0, 0, 0, 0, 0, 0, 0, 0, 0, 0, 0, 0, 0, 0, 0, 0, 0, 0, 0, 0, 0, 0, 0, 0, 0, 0, 0, 0, 0, 0, 0, 0, 0, 0, 0, 0, 0, 0, 0, 0, 0, 0, 0, 0, 0, 0, 0, 0, 0, 0, 0, 0, 0, 0, 0, 0, 0, 0, 0, 0, 0, 0, 0, 0, 0, 0, 0, 0, 0, 0, 0, 0, 0, 0, 0, 0, 0, 0, 0, 0, 0, 0, 0, 0, 0, 0, 0, 0, 0, 0, 0, 0, 0, 0, 0, 0, 0, 0, 0, 0, 0, 0, 0, 0, 0, 0, 0, 0, 0, 0, 0, 0, 0, 0, 0, 0, 0, 0, 0, 0, 0, 0, 0, 0, 0, 0, 0, 0, 0, 0, 0, 0, 0, 0, 0, 0, 0, 0, 0, 0, 0, 0, 0, 0, 0, 0, 0, 0, 0, 0, 0, 0, 0, 0, 0, 0, 0, 0, 0, 0, 0, 0, 0, 0, 0, 0, 0, 0, 0, 0, 0, 0, 0, 0, 0, 0, 0, 0, 0, 0, 0, 0, 0, 0, 0, 0, 0, 0, 0, 0, 0, 0, 0, 0, 0, 0, 0, 0, 0, 0, 0, 0, 0, 0, 0, 0, 0, 0, 0, 0, 0, 0, 0, 0, 0, 0, 0, 0, 0, 0, 0, 0, 0, 0, 0, 0, 0, 0, 0, 0, 0, 0, 0, 0, 0, 0, 0, 0, 0, 0, 0, 0, 0, 0, 0, 0, 0, 0, 0, 0, 0, 0, 0, 0, 0, 83, 116, 97, 110, 100, 97, 114, 100, 0, 0, 81, 92, 0, 112, 189, 182, 1, 0, 78, 0, 136, 1, 187, 5, 138, 5, 0, 184, 182, 0, 0, 127, 125, 0, 106, 0, 0, 0, 0, 0, 0, 0, 106, 0, 0, 0, 205, 205, 40, 0, 8, 1, 216, 0, 208, 172, 0, 0, 18, 211, 224, 0, 65, 117, 117, 205, 29, 182, 38, 255, 0, 0, 0, 0, 0, 1, 134, 190, 250, 48, 0, 112, 23, 215, 250, 48, 249, 5, 8, 0, 125, 8, 0, 0, 115, 0, 4, 0, 167, 0, 0, 0, 188, 4, 0, 0, 36, 216, 0, 0, 34, 233, 0, 0, 250, 48, 0, 129, 249, 5, 0, 1, 118, 125, 62, 14, 19, 27, 0, 0, 207, 146, 0, 0, 1, 0, 0, 0, 0, 0, 0, 0, 0, 0, 0, 0, 0, 0, 0, 0, 0, 0, 0, 0, 0, 0, 0, 0, 208, 79, 182, 1, 36, 0, 208, 0, 208, 0, 0, 127, 0, 135, 2, 127, 56, 207, 170, 86, 0, 0, 0, 0, 0, 0, 0, 0, 0, 0, 0, 0, 215, 78, 0, 0, 211, 92, 0, 0, 77, 146, 0, 0, 0, 0, 0, 0, 0, 0, 0, 0, 0, 0, 0, 0, 134, 5, 27, 0, 94, 0, 0, 0, 0, 0, 115, 0, 120, 71, 0, 0, 89, 0, 112, 0, 216, 216, 0, 1, 0, 0, 0, 0, 0, 0, 0, 0, 0, 0, 0, 0, 0, 0, 0, 0, 0, 0, 0, 0, 0, 0, 0, 0, 0, 0, 0, 0, 0, 0, 0, 0, 0, 0, 0, 0, 0, 0, 0, 0, 0, 0, 0, 0, 0, 0, 0, 0, 0, 119, 0, 0, 0, 0, 0, 0, 0, 0, 0, 0, 0, 0, 0, 0, 0, 0, 0, 0, 0, 0, 0, 0, 0, 0, 0, 0, 160, 64, 0, 0, 249, 5, 0, 0, 0, 0, 0, 0, 0, 0, 0, 0, 254, 250, 0, 0, 0, 0, 0, 0, 0, 0, 0, 0, 205, 1, 110, 102, 0, 0, 135, 0, 246, 0, 231, 1, 1, 0, 0, 0, 1, 0, 196, 234, 1,"],"exif:thumbnail:JPEGInterchangeFormat":["10928"],"exif:thumbnail:Make":["SONY"],"exif:CompressedBitsPerPixel":["4/1"],"exif:DateTime":["2013:01:24 09:50:34"],"exif:PrintImageMatching":["80, 114, 105, 110, 116, 73, 77, 0, 48, 51, 48, 48, 0, 0, 2, 0, 2, 0, 1, 0, 0, 0, 1, 1, 1, 0, 0, 0"],"exif:ImageDescription":["                               "],"exif:thumbnail:Model":["DSC-W350"],"exif:thumbnail:XResolution":["72/1"],"exif:thumbnail:Compression":["6"],"exif:Make":["SONY"],"exif:thumbnail:InteroperabilityVersion":["48, 49, 48, 48"]},"date":["2017-02-20 22:16:19","3012-02-01 04:00:00","4320-05-08 00:00:00"],"ascii":{"exif:MakerNote->ASCII":["SONY DSC +  0H \"X,DxD\\0@ABCDEFGHIJKLMNOPQRSTTP,)IIH2013:01:24 09:50:34 DC6303320222000StandardQ\\pN}jj(Auu&0p0}s$\"0v}>O$8VN\\M^sxGYpw@nf"],"exif:PrintImageMatching->ASCII":["PrintIM0300"],"exif:thumbnail:InteroperabilityVersion->ASCII":["0100"]}},"filesize_bytes":2405617,"filename":"lawa-bayliss.jpg","sha1":"fe69d722865679d4e20ba5b0549ec0bb7bb35af4","mimetype":"image/jpeg","url":"lawa.org.nz@@http://www.lawa.org.nz/media/2632407/lawa-bayliss.jpg"}