{"metadata":{"misc":{"dc_rights":["{}"],"__dict__":["{'stream': {'/Type': '/Metadata', '/Subtype': '/XML'}, 'rdfRoot': <DOM Element: rdf:RDF at 0x7f95529cac28>, 'cache': {}}"],"dc_format":["application/pdf"],"xmpmm_instanceId":["uuid:19cdf5c9-a54c-4924-b548-99315fbcf2f7"],"dc_relation":["[]"],"pdf_keywords":[""],"dc_source":["None"],"dc_language":["[]"],"rdfRoot":[{"rdf:RDF":{"@xmlns:rdf":"http://www.w3.org/1999/02/22-rdf-syntax-ns#","rdf:Description":[{"@rdf:about":"","@xmlns:xap":"http://ns.adobe.com/xap/1.0/","xap:CreateDate":"2012-06-27T13:51:27Z","xap:CreatorTool":"Microsoft Word","xap:ModifyDate":"2012-06-27T15:56:15+02:00","xap:MetadataDate":"2012-06-27T15:56:15+02:00"},{"@rdf:about":"","@xmlns:dc":"http://purl.org/dc/elements/1.1/","dc:format":"application/pdf","dc:creator":{"rdf:Seq":{"rdf:li":"Jonathan Lynn"}},"dc:title":{"rdf:Alt":{"rdf:li":{"@xml:lang":"x-default","#text":"Microsoft Word - 120627 review completion press release v7 final.doc"}}}},{"@rdf:about":"","@xmlns:pdf":"http://ns.adobe.com/pdf/1.3/","pdf:Keywords":null,"pdf:Producer":"Mac OS X 10.6.8 Quartz PDFContext"},{"@rdf:about":"","@xmlns:xapMM":"http://ns.adobe.com/xap/1.0/mm/","xapMM:DocumentID":"uuid:cc173f84-35d8-4367-8412-106ff637d615","xapMM:InstanceID":"uuid:19cdf5c9-a54c-4924-b548-99315fbcf2f7"}]}}],"__doc__":["\n    An object that represents Adobe XMP metadata.\n    Usually accessed by :meth:`getXmpMetadata()<PyPDF2.PdfFileReader.getXmpMetadata>`\n    "],"__weakref__":["None"],"dc_identifier":["None"],"info":[{"/CreationDate":"D:20120627135127Z","/ModDate":"D:20120627155615+02'00'","/AAPL:Keywords":[],"/Keywords":"","/Title":"Microsoft Word - 120627 review completion press release v7 final.doc","/Creator":"Microsoft Word","/Author":"Jonathan Lynn","/Producer":"Mac OS X 10.6.8 Quartz PDFContext"}],"dc_description":["{}"],"dc_subject":["[]"],"xmpmm_documentId":["uuid:cc173f84-35d8-4367-8412-106ff637d615"],"cache":["{}"],"pdf_pdfversion":["None"],"dc_title":["{'x-default': 'Microsoft Word - 120627 review completion press release v7 final.doc'}"],"xmp_creatorTool":["Microsoft Word"],"dc_contributor":["[]"],"dc_creator":["['Jonathan Lynn']"],"dc_type":["[]"],"stream":["{'/Type': '/Metadata', '/Subtype': '/XML'}"],"dc_coverage":["None"],"dc_publisher":["[]"],"__module__":["PyPDF2.xmp"],"pdf_producer":["Mac OS X 10.6.8 Quartz PDFContext"],"custom_properties":["{}"],"dc_date":["[]"]},"date":["2017-05-07 12:06:16.086688","2017-05-07 12:06:16.086799","2017-05-07 12:06:16.086849"]},"mimetype":"application/pdf","filesize_bytes":141155,"sha1":"2a8df0b2711e268cee9ccaa9e27065d830697f02","filename":"IAC_PR_Completion.pdf","url":"climaterealists.org.nz@@http://www.ipcc.ch/pdf/IAC_report/IAC_PR_Completion.pdf"}