{"mimetype":"application/pdf","children":[{"misc":{"stRef:documentID":["xmp.did:0A801174072068118083E6D470008243"],"xmpMM:InstanceID":["xmp.iid:2B02D7182B2068118083E6D470008243"],"xmp:CreateDate":["2011-09-21T15:40:20+12:00"],"xmp:CreatorTool":["Adobe Illustrator CS5.1"],"illustrator:StartupProfile":["Print"],"stRef:originalDocumentID":["uuid:5D20892493BFDB11914A8590D31508C8"],"xmp:MetadataDate":["2011-09-21T15:40:20+12:00"],"stRef:instanceID":["xmp.iid:0A801174072068118083E6D470008243"],"stRef:renditionClass":["proof:pdf"],"xmpMM:OriginalDocumentID":["uuid:5D20892493BFDB11914A8590D31508C8"],"xmp:ModifyDate":["2011-09-21T03:40:24Z"],"pdf:Producer":["Adobe PDF library 9.90"],"xmpMM:RenditionClass":["proof:pdf"],"xmpMM:DocumentID":["xmp.did:2B02D7182B2068118083E6D470008243"]},"date":["2011-09-21T15:40:20"]}],"metadata":{"misc":{"custom_properties":["{}"],"dc_rights":["{}"],"dc_publisher":["[]"],"dc_language":["[]"],"dc_type":["[]"],"cache":["{}"],"dc_contributor":["[]"],"dc_relation":["[]"],"dc_description":["{}"],"dc_title":["{}"],"dc_date":["[]"],"dc_subject":["[]"],"dc_creator":["[]"]},"software":["Microsoft® Word 2010"],"date":["2013-08-14T18:07:55+12:00","2013-08-15T08:35:15+12:00"]},"filename":"Commerce%2bCommission%2bDraft%2bReport%2b-%2bReview%2bof%2bMilk%2bPrice%2bCalc%2b2012-13.pdf","sha1":"7fbe7a314435a14462cb691ea8e66395631d4a1c","filesize_bytes":1506715,"url":"fonterra.com@@https://www.fonterra.com/content/dam/fonterradotcom-www2/files/financial-docs/industry-regulations/commerce-commission/Commerce%2bCommission%2bDraft%2bReport%2b-%2bReview%2bof%2bMilk%2bPrice%2bCalc%2b2012-13.pdf"}