{"sha1":"627c3e0c89e49b289855375335f20ec3ed6e6576","metadata":{"misc":{"dc_type":["[]"],"dc_contributor":["[]"],"custom_properties":["{}"],"dc_rights":["{}"],"dc_language":["[]"],"dc_title":["{}"],"dc_description":["{}"],"dc_date":["[]"],"dc_creator":["[]"],"dc_relation":["[]"],"dc_publisher":["[]"],"dc_subject":["[]"],"cache":["{}"]},"software":["Adobe InDesign CS6 (Windows)","Adobe PDF Library 10.0.1"],"date":["2014-10-13T15:39:28+13:00","2014-10-13T15:40:00+13:00"]},"filesize_bytes":2521083,"children":[{"date":[]},{"date":[]},{"date":[]},{"date":[]},{"date":[]},{"date":[]},{"date":[]},{"date":[]},{"date":[]},{"date":[]},{"date":[]}],"mimetype":"application/pdf","filename":"Global+Dairy+Update+October+2014.pdf","url":"fonterra.com@@http://www2.fonterra.com/files/financial-docs/global-dairy-updates/Global+Dairy+Update+October+2014.pdf"}