{"filesize_bytes":1351310,"metadata":{"date":["2015-10-16T15:58:38+13:00","2015-10-16T15:58:43+13:00"],"misc":{"dc_relation":["[]"],"custom_properties":["{}"],"dc_date":["[]"],"dc_title":["{}"],"dc_description":["{}"],"dc_rights":["{}"],"cache":["{}"],"dc_contributor":["[]"],"dc_publisher":["[]"],"dc_type":["[]"],"dc_subject":["[]"],"dc_language":["[]"],"dc_creator":["[]"]},"software":["Adobe InDesign CC 2015 (Macintosh)","Adobe PDF Library 15.0"]},"sha1":"3f01b1ebad7de84ad735021debf9ce73ef30edf6","children":[{"date":[]},{"date":[]},{"date":[]},{"date":[]},{"date":[]},{"date":[]},{"date":[]},{"date":[]},{"date":[]}],"mimetype":"application/pdf","filename":"global-dairy-update-october-2015.pdf","url":"fonterra.com@@http://www2.fonterra.com/files/2015-10/global-dairy-update-october-2015.pdf"}