{"metadata":{"misc":{"dc_contributor":["[]"],"dc_description":["{}"],"dc_relation":["[]"],"dc_type":["[]"],"dc_rights":["{}"],"dc_language":["[]"],"dc_subject":["[\"AU Fonterra Shareholders' Fund Prospectus and Investment Statement\"]"],"cache":["{}"],"dc_date":["[]"],"dc_publisher":["[]"],"custom_properties":["{}"]},"people":["Fonterra Co-operative Group Limited","['\\n            \\n         ']"],"software":["Adobe InDesign CS5 (7.0.4)","Adobe PDF Library 9.9"],"date":["2012-11-02T13:59:28+13:00","2012-11-04T11:35:16+11:00"]},"filename":"fsf-prospectus.pdf","mimetype":"application/pdf","filesize_bytes":8147407,"sha1":"3b4f9a27d22306a6ecafb8b195a0aa5f5987c180","children":[{"date":[]},{"date":[]},{"date":[]},{"date":[]},{"date":[]},{"date":[]},{"date":[]},{"date":[]},{"date":[]},{"date":[]},{"date":[]},{"date":[]},{"date":[]},{"date":[]},{"date":[]},{"date":[]},{"date":[]},{"date":[]},{"date":[]},{"date":[]},{"date":[]},{"date":[]},{"date":[]},{"date":[]},{"date":[]},{"date":[]},{"date":[]},{"date":[]},{"date":[]},{"date":[]},{"date":[]},{"date":[]},{"date":[]},{"date":[]},{"date":[]},{"date":[]},{"date":[]},{"date":[]},{"date":[]},{"date":[]},{"date":[]},{"date":[]},{"date":[]},{"date":[]},{"date":[]},{"date":[]},{"date":[]},{"date":[]},{"date":[]},{"date":[]},{"date":[]},{"date":[]},{"date":[]},{"date":[]},{"date":[]},{"date":[]},{"date":[]},{"date":[]},{"date":[]},{"date":[]},{"date":[]},{"date":[]},{"date":[]},{"date":[]},{"date":[]},{"date":[]},{"date":[]},{"date":[]},{"date":[]},{"date":[]},{"date":[]},{"date":[]},{"date":[]},{"date":[]},{"date":[]},{"date":[]},{"date":[]},{"date":[]},{"date":[]},{"date":[]},{"date":[]},{"date":[]},{"date":[]},{"date":[]},{"date":[]},{"date":[]},{"date":[]},{"date":[]},{"date":[]},{"date":[]},{"date":[]},{"date":[]},{"date":[]},{"date":[]},{"date":[]},{"date":[]},{"date":[]},{"date":[]},{"date":[]},{"date":[]},{"date":[]},{"date":[]},{"date":[]},{"date":[]},{"date":[]},{"date":[]},{"date":[]},{"date":[]},{"date":[]},{"date":[]},{"date":[]},{"date":[]},{"date":[]},{"date":[]},{"date":[]},{"date":[]},{"date":[]},{"date":[]},{"date":[]}],"url":"fonterra.com@@https://www2.fonterra.com/files/financial-docs/fsf-prospectus.pdf"}