{"filename":"4116+Risk+Management_web.pdf","mimetype":"application/pdf","sha1":"5c714b56619288eb30c01ce946b89b299b2561cf","metadata":{"info":{"/CreationDate":"D:20100215092218+13'00'","/ModDate":"D:20120703115634+12'00'","/Creator":"Adobe InDesign CS3 (5.0.4)","/Producer":"Adobe PDF Library 8.0","/Trapped":"/False"},"xmp":{"cache":{},"__module__":"PyPDF2.xmp","__dict__":"{'cache': {}, 'stream': {'/Type': '/Metadata', '/Subtype': '/XML'}, 'rdfRoot': <DOM Element: rdf:RDF at 0x7f78bda145a0>}","xmp_metadataDate":"None","rdfRoot":{"rdf:RDF":{"@xmlns:rdf":"http://www.w3.org/1999/02/22-rdf-syntax-ns#","rdf:Description":[{"@rdf:about":"","@xmlns:pdf":"http://ns.adobe.com/pdf/1.3/","pdf:Producer":"Adobe PDF Library 8.0"},{"@rdf:about":"","@xmlns:xap":"http://ns.adobe.com/xap/1.0/","xap:CreatorTool":"Adobe InDesign CS3 (5.0.4)","xap:CreateDate":"2010-02-15T09:22:18+13:00","xap:ModifyDate":"2012-07-03T11:56:34+12:00"}]}},"stream":"{'/Type': '/Metadata', '/Subtype': '/XML'}","dc_source":"None","dc_language":[],"dc_coverage":"None","dc_rights":{},"dc_subject":[],"dc_creator":[],"dc_type":[],"dc_relation":[],"pdf_producer":"Adobe PDF Library 8.0","__weakref__":"None","dc_publisher":[],"dc_format":"None","__doc__":"\n    An object that represents Adobe XMP metadata.\n    Usually accessed by :meth:`getXmpMetadata()<PyPDF2.PdfFileReader.getXmpMetadata>`\n    ","dc_title":{},"dc_description":{},"dc_contributor":[],"dc_date":[],"xmp_modifyDate":"2016-06-30 22:22:01.078367","xmpmm_documentId":"None","pdf_keywords":"None","dc_identifier":"None","xmpmm_instanceId":"None","pdf_pdfversion":"None","xmp_creatorTool":"Adobe InDesign CS3 (5.0.4)","custom_properties":{},"xmp_createDate":"2016-06-30 22:22:01.078257"}},"filesize_bytes":1528488,"url":"fonterra.com@@https://www.fonterra.com/wps/wcm/connect/598b92ba-cea3-410d-83fe-8a98f25f3beb/4116+Risk+Management_web.pdf?MOD=AJPERES"}