{"mimetype":"image/jpeg","sha1":"0b8f7d7be9eeed62224df53f2149f57cf941a8b5","filename":"Full+profile+pic_0000_Rob_Spurway_185.jpg","filesize_bytes":49127,"metadata":{"exif:PhotometricInterpretation":"2","exif:DateTimeDigitized":"2013:06:21 08:57:20","exif:DateTime":"2014:10:14 16:46:02","exif:Artist":"Bruce Jarvis","icc:manufacturer":"Adobe RGB (1998)","icc:description":"Adobe RGB (1998)","exif:BitsPerSample":"8, 8, 8","exif:Software":"Adobe Photoshop CS6 (Windows)","exif:DateTimeOriginal":"2013:06:21 08:57:20","icc:copyright":"Copyright 1999 Adobe Systems Incorporated","exif:Make":"Canon","exif:Model":"Canon EOS 5D Mark III","exif:Copyright":"Copyright - Bruce Jarvis","icc:model":"Adobe RGB (1998)","exif:SamplesPerPixel":"3"},"url":"fonterra.com@@http://www.fonterra.com/wps/wcm/connect/5fd0e765-4ea9-47ae-af1d-f2620ade7c43/Full+profile+pic_0000_Rob_Spurway_185.jpg?MOD=AJPERES&CACHEID=5fd0e765-4ea9-47ae-af1d-f2620ade7c43"}